base_model_trpgner/__init__.py
base_model_trpgner/inference/__init__.py
base_model_trpgner/training/__init__.py
base_model_trpgner/utils/__init__.py
base_model_trpgner-0.1.10.dist-info/METADATA
base_model_trpgner-0.1.10.dist-info/WHEEL
base_model_trpgner-0.1.10.dist-info/licenses/LICENSE
base_model_trpgner-0.1.10.dist-info/RECORD
