Metadata-Version: 2.4
Name: base-model-trpgner
Version: 0.1.10
Summary: HydroRoll TRPG NER 模型 - 桌上角色扮演游戏日志命名实体识别
Project-URL: Homepage, https://ailab.hydroroll.team/
Project-URL: Repository, https://github.com/HydroRoll-Team/base-model
Project-URL: Documentation, https://ailab.hydroroll.team/
Project-URL: Issues, https://github.com/HydroRoll-Team/base-model/issues
Author-email: HsiangNianian <leader@hydroroll.team>
License: AFL-3.0
License-File: LICENSE
Keywords: chinese,hydroroll,ner,nlp,onnx,robot framework,trpg
Classifier: Development Status :: 3 - Alpha
Classifier: Intended Audience :: Developers
Classifier: License :: OSI Approved :: Academic Free License (AFL)
Classifier: Operating System :: OS Independent
Classifier: Programming Language :: Python :: 3
Classifier: Programming Language :: Python :: 3.12
Classifier: Topic :: Scientific/Engineering :: Artificial Intelligence
Classifier: Topic :: Text Processing :: Linguistic
Requires-Python: >=3.10
Requires-Dist: aiohttp>=3.13.2
Requires-Dist: numpy>=1.24.0
Requires-Dist: ollama>=0.6.1
Requires-Dist: onnxruntime>=1.23.2
Requires-Dist: transformers>=4.57.3
Provides-Extra: all
Requires-Dist: accelerate>=0.27.0; extra == 'all'
Requires-Dist: black>=24.0.0; extra == 'all'
Requires-Dist: datasets>=2.18.0; extra == 'all'
Requires-Dist: dotenv>=0.9.9; extra == 'all'
Requires-Dist: gradio>=6.2.0; extra == 'all'
Requires-Dist: onnxscript>=0.5.7; extra == 'all'
Requires-Dist: pytest>=8.0.0; extra == 'all'
Requires-Dist: ruff>=0.1.0; extra == 'all'
Requires-Dist: scikit-learn>=1.4.0; extra == 'all'
Requires-Dist: torch>=2.9.1; extra == 'all'
Requires-Dist: tqdm>=4.66.0; extra == 'all'
Provides-Extra: dev
Requires-Dist: accelerate>=0.27.0; extra == 'dev'
Requires-Dist: black>=24.0.0; extra == 'dev'
Requires-Dist: datasets>=2.18.0; extra == 'dev'
Requires-Dist: dotenv>=0.9.9; extra == 'dev'
Requires-Dist: onnxscript>=0.5.7; extra == 'dev'
Requires-Dist: pytest>=8.0.0; extra == 'dev'
Requires-Dist: ruff>=0.1.0; extra == 'dev'
Requires-Dist: torch>=2.9.1; extra == 'dev'
Requires-Dist: tqdm>=4.66.0; extra == 'dev'
Provides-Extra: train
Requires-Dist: accelerate>=0.27.0; extra == 'train'
Requires-Dist: datasets>=2.18.0; extra == 'train'
Requires-Dist: onnxscript>=0.5.7; extra == 'train'
Requires-Dist: torch>=2.9.1; extra == 'train'
Requires-Dist: tqdm>=4.66.0; extra == 'train'
Provides-Extra: webui
Requires-Dist: accelerate>=0.27.0; extra == 'webui'
Requires-Dist: datasets>=2.18.0; extra == 'webui'
Requires-Dist: gradio>=6.2.0; extra == 'webui'
Requires-Dist: onnxscript>=0.5.7; extra == 'webui'
Requires-Dist: scikit-learn>=1.4.0; extra == 'webui'
Requires-Dist: torch>=2.9.1; extra == 'webui'
Requires-Dist: tqdm>=4.66.0; extra == 'webui'
